odoo8_addon_pos_autoreconcile-8.0.0.1.0-py2.7-nspkg.pth
odoo_addons/pos_autoreconcile/__openerp__.py
odoo_addons/pos_autoreconcile/__init__.py
odoo_addons/pos_autoreconcile/README.rst
odoo_addons/pos_autoreconcile/security/ir.model.access.csv
odoo_addons/pos_autoreconcile/i18n/nl_NL.po
odoo_addons/pos_autoreconcile/i18n/it.po
odoo_addons/pos_autoreconcile/i18n/es.po
odoo_addons/pos_autoreconcile/i18n/sl.po
odoo_addons/pos_autoreconcile/i18n/fr.po
odoo_addons/pos_autoreconcile/model/point_of_sale.py
odoo_addons/pos_autoreconcile/model/__init__.py
odoo8_addon_pos_autoreconcile-8.0.0.1.0.dist-info/top_level.txt
odoo8_addon_pos_autoreconcile-8.0.0.1.0.dist-info/WHEEL
odoo8_addon_pos_autoreconcile-8.0.0.1.0.dist-info/RECORD
odoo8_addon_pos_autoreconcile-8.0.0.1.0.dist-info/metadata.json
odoo8_addon_pos_autoreconcile-8.0.0.1.0.dist-info/DESCRIPTION.rst
odoo8_addon_pos_autoreconcile-8.0.0.1.0.dist-info/METADATA
odoo8_addon_pos_autoreconcile-8.0.0.1.0.dist-info/namespace_packages.txt
