Metadata-Version: 2.0
Name: odoo8-addon-pos-autoreconcile
Version: 8.0.0.1.0
Summary: POS Autoreconcile
Home-page: http://www.versada.lt
Author: UNKNOWN
Author-email: UNKNOWN
License: UNKNOWN
Platform: UNKNOWN
Requires-Dist: odoo (<9.0a,>=8.0a)
Classifier: Programming Language :: Python :: 2.7
Classifier: Framework :: Odoo
